Metadata-Version: 1.1
Name: batchproc
Version: 0.1.1
Summary: Simple batch processing framework.
Home-page: https://github.com/metavee/batchproc
Author: Robin Neufeld
Author-email: raeneufe@uwaterloo.ca
License: MIT
Platform: UNKNOWN
Classifier: Development Status :: 3 - Alpha
Classifier: Intended Audience :: Developers
Classifier: Intended Audience :: Science/Research
Classifier: License :: OSI Approved :: MIT License
Classifier: Programming Language :: Python :: 2.7
Classifier: Programming Language :: Python :: 3
Classifier: Topic :: Software Development :: Libraries :: Python Modules
